<?xml version="1.0" encoding="utf-8" ?>
<elements>
	<info>
		<update version="0.0.1">
			<file name="sources.xml" url="https://raw.githubusercontent.com/AuroraLegacy/elements/master/core/players-handbook/source.xml" />
		</update>
	</info>
	<element name="2024 Player’s Handbook" type="Source" source="Core" id="ID_WOTC_SOURCE_2024PLAYERS_HANDBOOK">
		<description>
			<p><strong>The player's handbook for DnD 5E released in 2024.</strong></p>
			<p>The <i>Player’s Handbook</i> is the essential reference for every Dungeons &amp; Dragons roleplayer. It contains rules for character creation and advancement, backgrounds and skills, exploration and combat, equipment, spells, and much more. Use this book to create exciting characters from among the most iconic D&amp;D races and classes.</p>
			<p>Dungeons &amp; Dragons immerses you in a world of adventure. Explore ancient ruins and deadly dungeons. Battle monsters while searching for legendary treasures. Gain experience and power as you trek across uncharted lands with your companions.</p>
			<p>The world needs heroes. Will you answer the call?</p>
		</description>
		<setters>
			<set name="abbreviation">2024PHB</set>
			<set name="url">https://github.com/Leadvillite?tab=repositories</set>
			<set name="image"></set>
			<set name="author" abbreviation="WOTC" url="http://dnd.wizards.com">Wizards of the Coast</set>
			<set name="official">true</set>
			<set name="core">true</set>
			<set name="release">20240819</set>
		</setters>
	</element>
</elements>
